{
  "props": [
  {
    "name": "dark",
    "global": false,
    "description": "",
    "tags": [],
    "required": true,
    "type": "string",
    "schema": "string"
  },
  {
    "name": "light",
    "global": false,
    "description": "",
    "tags": [],
    "required": true,
    "type": "string",
    "schema": "string"
  }
],
  "slots": [],
  "events": [],
  "exposed": [
  {
    "name": "dark",
    "type": "string",
    "description": "",
    "schema": "string"
  },
  {
    "name": "light",
    "type": "string",
    "description": "",
    "schema": "string"
  }
]
}
